jacoco_badge_generator/__init__.py
jacoco_badge_generator/__main__.py
jacoco_badge_generator/coverage_badges.py
jacoco_badge_generator/text_length.py
jacoco_badge_generator-2.12.1.dist-info/METADATA
jacoco_badge_generator-2.12.1.dist-info/WHEEL
jacoco_badge_generator-2.12.1.dist-info/licenses/LICENSE
jacoco_badge_generator-2.12.1.dist-info/RECORD
