Metadata-Version: 2.4
Name: jacoco-badge-generator
Version: 2.12.1
Summary: JaCoCo coverage badges (SVG format), and coverage checks (e.g., decreasing coverage and minimum coverage)
Project-URL: Information Page, https://actions.cicirello.org/jacoco-badge-generator/
Project-URL: GitHub Repository, https://github.com/cicirello/jacoco-badge-generator
Project-URL: Bug Tracker, https://github.com/cicirello/jacoco-badge-generator/issues
Project-URL: Changelog, https://github.com/cicirello/jacoco-badge-generator/blob/main/CHANGELOG.md
Author-email: "Vincent A. Cicirello" <development@cicirello.org>
License-File: LICENSE
Keywords: C0 coverage,C1 coverage,JVM,Java,Kotlin,Scala,badge generator,badges,branches coverage,coverage,coverage reports,instructions coverage,jacoco,testing
Classifier: Intended Audience :: Developers
Classifier: License :: OSI Approved :: MIT License
Classifier: Operating System :: OS Independent
Classifier: Programming Language :: Python :: 3
Classifier: Topic :: Software Development :: Testing
Requires-Python: >=3.8
